[{"url":"https:\/\/www.youtube.com\/watch?v=5nyCo-6R1bE","alternative_url":"https:\/\/invidious.zee.li\/watch?v=5nyCo-6R1bE","date":"2021-03-22T23:43:46+00:00","traffic":772559},{"url":"https:\/\/www.youtube.com\/watch?v=h6O5IQgF7TU","alternative_url":"https:\/\/invidious.himiko.cloud\/watch?v=h6O5IQgF7TU","date":"2021-03-22T14:42:39+00:00","traffic":521772},{"url":"https:\/\/www.youtube.com\/watch?v=dCAkb41os4w","alternative_url":"https:\/\/invidious.tube\/watch?v=dCAkb41os4w","date":"2021-03-22T16:02:28+00:00","traffic":515777},{"url":"https:\/\/www.youtube.com\/watch?v=cibdBr9TkEo","alternative_url":"https:\/\/ytprivate.com\/watch?v=cibdBr9TkEo","date":"2021-03-22T16:41:55+00:00","traffic":472067},{"url":"https:\/\/www.youtube.com\/watch?v=V3rDBZYSIxA","alternative_url":"https:\/\/yewtu.be\/watch?v=V3rDBZYSIxA","date":"2021-03-23T08:43:46+00:00","traffic":453261},{"url":"https:\/\/www.youtube.com\/watch?v=d_4eekPQdn4","alternative_url":"https:\/\/invidious.048596.xyz\/watch?v=d_4eekPQdn4","date":"2021-03-22T17:42:39+00:00","traffic":395469},{"url":"https:\/\/www.youtube.com\/watch?v=-9KU2MEULy8","alternative_url":"https:\/\/invidious.tube\/watch?v=-9KU2MEULy8","date":"2021-03-22T14:42:39+00:00","traffic":375895},{"url":"https:\/\/www.youtube.com\/watch?v=pSeWreDOXL4","alternative_url":"https:\/\/invidious.himiko.cloud\/watch?v=pSeWreDOXL4","date":"2021-03-23T05:14:47+00:00","traffic":349071},{"url":"https:\/\/www.youtube.com\/watch?v=G1qDfbK5pMM","alternative_url":"https:\/\/vid.mint.lgbt\/watch?v=G1qDfbK5pMM","date":"2021-03-22T15:42:39+00:00","traffic":309029},{"url":"https:\/\/www.youtube.com\/watch?v=Pa1-F-DAJ_c","alternative_url":"https:\/\/tube.incog.host\/watch?v=Pa1-F-DAJ_c","date":"2021-03-22T16:42:39+00:00","traffic":275553},{"url":"https:\/\/www.youtube.com\/watch?v=NQB5W6BmYg8","alternative_url":"https:\/\/au.ytprivate.com\/watch?v=NQB5W6BmYg8","date":"2021-03-23T08:42:39+00:00","traffic":245078},{"url":"https:\/\/www.youtube.com\/watch?v=OkM_PdbLuzw","alternative_url":"https:\/\/invidious.048596.xyz\/watch?v=OkM_PdbLuzw","date":"2021-03-22T15:06:42+00:00","traffic":224151},{"url":"https:\/\/www.youtube.com\/watch?v=wC18Gi_FrOg","alternative_url":"https:\/\/invidious.tube\/watch?v=wC18Gi_FrOg","date":"2021-03-22T17:06:42+00:00","traffic":220037},{"url":"https:\/\/www.youtube.com\/watch?v=vGFVHB-YrsA","alternative_url":"https:\/\/invidious.zee.li\/watch?v=vGFVHB-YrsA","date":"2021-03-23T07:06:42+00:00","traffic":216448},{"url":"https:\/\/www.youtube.com\/watch?v=zi1h4fGKZ1g","alternative_url":"https:\/\/vid.puffyan.us\/watch?v=zi1h4fGKZ1g","date":"2021-03-22T22:02:33+00:00","traffic":215939},{"url":"https:\/\/www.youtube.com\/watch?v=OUZ0_fwuZiw","alternative_url":"https:\/\/vid.mint.lgbt\/watch?v=OUZ0_fwuZiw","date":"2021-03-22T19:02:33+00:00","traffic":210503},{"url":"https:\/\/www.youtube.com\/watch?v=e34RQfaYGOc","alternative_url":"https:\/\/invidious.048596.xyz\/watch?v=e34RQfaYGOc","date":"2021-03-23T07:02:21+00:00","traffic":209358},{"url":"https:\/\/www.youtube.com\/watch?v=zuW90OSUz8E","alternative_url":"https:\/\/tube.incog.host\/watch?v=zuW90OSUz8E","date":"2021-03-22T19:37:03+00:00","traffic":205969},{"url":"https:\/\/www.youtube.com\/watch?v=FQxPCnqAqpc","alternative_url":"https:\/\/invidious.zee.li\/watch?v=FQxPCnqAqpc","date":"2021-03-23T06:42:39+00:00","traffic":196582},{"url":"https:\/\/www.youtube.com\/watch?v=aIFX-VagRhI","alternative_url":"https:\/\/invidious.himiko.cloud\/watch?v=aIFX-VagRhI","date":"2021-03-22T17:14:47+00:00","traffic":186135},{"url":"https:\/\/www.youtube.com\/watch?v=jIjnhS6mpYw","alternative_url":"https:\/\/tube.incog.host\/watch?v=jIjnhS6mpYw","date":"2021-03-22T18:06:42+00:00","traffic":183271},{"url":"https:\/\/www.youtube.com\/watch?v=Twnpy1pbV8k","alternative_url":"https:\/\/ytprivate.com\/watch?v=Twnpy1pbV8k","date":"2021-03-23T03:06:42+00:00","traffic":170951},{"url":"https:\/\/www.youtube.com\/watch?v=Myxb6owD6XM","alternative_url":"https:\/\/tube.incog.host\/watch?v=Myxb6owD6XM","date":"2021-03-22T19:42:39+00:00","traffic":170549},{"url":"https:\/\/www.youtube.com\/watch?v=Vz9rxNWjGVA","alternative_url":"https:\/\/invidious.zee.li\/watch?v=Vz9rxNWjGVA","date":"2021-03-22T15:37:03+00:00","traffic":169897},{"url":"https:\/\/www.youtube.com\/watch?v=k-fk93MzHkw","alternative_url":"https:\/\/invidious.kavin.rocks\/watch?v=k-fk93MzHkw","date":"2021-03-22T20:57:42+00:00","traffic":169740},{"url":"https:\/\/www.youtube.com\/watch?v=-POEnCGwpY4","alternative_url":"https:\/\/ytprivate.com\/watch?v=-POEnCGwpY4","date":"2021-03-22T17:42:39+00:00","traffic":169642},{"url":"https:\/\/www.youtube.com\/watch?v=W0SJ4VnP6o8","alternative_url":"https:\/\/vid.puffyan.us\/watch?v=W0SJ4VnP6o8","date":"2021-03-22T20:41:02+00:00","traffic":168637},{"url":"https:\/\/www.youtube.com\/watch?v=_DbpvAwKIpM","alternative_url":"https:\/\/ytprivate.com\/watch?v=_DbpvAwKIpM","date":"2021-03-22T23:43:46+00:00","traffic":167574},{"url":"https:\/\/www.youtube.com\/watch?v=3PjrwoKLVHU","alternative_url":"https:\/\/vid.mint.lgbt\/watch?v=3PjrwoKLVHU","date":"2021-03-22T23:43:46+00:00","traffic":167064},{"url":"https:\/\/www.youtube.com\/watch?v=nNqR_AJSkLE","alternative_url":"https:\/\/au.ytprivate.com\/watch?v=nNqR_AJSkLE","date":"2021-03-22T23:42:39+00:00","traffic":164195},{"url":"https:\/\/www.youtube.com\/watch?v=EfJaxqNXaJg","alternative_url":"https:\/\/vid.mint.lgbt\/watch?v=EfJaxqNXaJg","date":"2021-03-22T15:43:46+00:00","traffic":163725},{"url":"https:\/\/www.youtube.com\/watch?v=KXGU0gYosjY","alternative_url":"https:\/\/ytprivate.com\/watch?v=KXGU0gYosjY","date":"2021-03-23T11:06:42+00:00","traffic":151524},{"url":"https:\/\/www.youtube.com\/watch?v=tUaLumN--rc","alternative_url":"https:\/\/au.ytprivate.com\/watch?v=tUaLumN--rc","date":"2021-03-22T22:42:39+00:00","traffic":149181},{"url":"https:\/\/www.youtube.com\/watch?v=8iIpWbz65rg","alternative_url":"https:\/\/ytprivate.com\/watch?v=8iIpWbz65rg","date":"2021-03-22T15:02:33+00:00","traffic":147975},{"url":"https:\/\/www.youtube.com\/watch?v=xCqay65whkE","alternative_url":"https:\/\/invidious.kavin.rocks\/watch?v=xCqay65whkE","date":"2021-03-22T15:06:42+00:00","traffic":140543},{"url":"https:\/\/www.youtube.com\/watch?v=abn8U2bLLBE","alternative_url":"https:\/\/ytprivate.com\/watch?v=abn8U2bLLBE","date":"2021-03-22T15:43:46+00:00","traffic":139029},{"url":"https:\/\/www.youtube.com\/watch?v=rnbU1SclF-s","alternative_url":"https:\/\/ytprivate.com\/watch?v=rnbU1SclF-s","date":"2021-03-22T22:43:46+00:00","traffic":138506},{"url":"https:\/\/www.youtube.com\/watch?v=R2jKOdH8PWU","alternative_url":"https:\/\/vid.puffyan.us\/watch?v=R2jKOdH8PWU","date":"2021-03-22T16:14:47+00:00","traffic":136251},{"url":"https:\/\/www.youtube.com\/watch?v=HY0Mu4IIjSI","alternative_url":"https:\/\/invidious.zee.li\/watch?v=HY0Mu4IIjSI","date":"2021-03-22T16:02:33+00:00","traffic":128125},{"url":"https:\/\/www.youtube.com\/watch?v=tj2KbEgUBnE","alternative_url":"https:\/\/au.ytprivate.com\/watch?v=tj2KbEgUBnE","date":"2021-03-23T03:42:39+00:00","traffic":125631},{"url":"https:\/\/www.youtube.com\/watch?v=2bGGhFbAs3o","alternative_url":"https:\/\/au.ytprivate.com\/watch?v=2bGGhFbAs3o","date":"2021-03-22T15:06:42+00:00","traffic":125196},{"url":"https:\/\/www.youtube.com\/watch?v=mfLO3Ainxk0","alternative_url":"https:\/\/invidious.048596.xyz\/watch?v=mfLO3Ainxk0","date":"2021-03-23T08:06:42+00:00","traffic":123651},{"url":"https:\/\/www.youtube.com\/watch?v=P4t1JvwHXU8","alternative_url":"https:\/\/au.ytprivate.com\/watch?v=P4t1JvwHXU8","date":"2021-03-23T10:02:33+00:00","traffic":123152},{"url":"https:\/\/www.youtube.com\/watch?v=RvAUnRucKKY","alternative_url":"https:\/\/ytprivate.com\/watch?v=RvAUnRucKKY","date":"2021-03-23T12:42:39+00:00","traffic":121042},{"url":"https:\/\/www.youtube.com\/watch?v=lHHyhztXW-o","alternative_url":"https:\/\/invidious.snopyta.org\/watch?v=lHHyhztXW-o","date":"2021-03-22T22:57:42+00:00","traffic":120941},{"url":"https:\/\/www.youtube.com\/watch?v=Tcsj9rCQjb0","alternative_url":"https:\/\/invidious.snopyta.org\/watch?v=Tcsj9rCQjb0","date":"2021-03-22T18:06:42+00:00","traffic":119498},{"url":"https:\/\/www.youtube.com\/watch?v=5tSPqIsr4XM","alternative_url":"https:\/\/invidious.tube\/watch?v=5tSPqIsr4XM","date":"2021-03-22T15:06:42+00:00","traffic":117478},{"url":"https:\/\/www.youtube.com\/watch?v=tSBIkMDDcEc","alternative_url":"https:\/\/invidious.kavin.rocks\/watch?v=tSBIkMDDcEc","date":"2021-03-22T14:42:39+00:00","traffic":114990},{"url":"https:\/\/www.youtube.com\/watch?v=LYSufxVZXAQ","alternative_url":"https:\/\/invidious.snopyta.org\/watch?v=LYSufxVZXAQ","date":"2021-03-23T13:40:42+00:00","traffic":104900},{"url":"https:\/\/www.youtube.com\/watch?v=nH32kTt1NoU","alternative_url":"https:\/\/tube.incog.host\/watch?v=nH32kTt1NoU","date":"2021-03-22T14:45:18+00:00","traffic":101647},{"url":"https:\/\/www.youtube.com\/watch?v=40VqaY3ROos","alternative_url":"https:\/\/invidious.snopyta.org\/watch?v=40VqaY3ROos","date":"2021-03-23T07:06:42+00:00","traffic":100271},{"url":"https:\/\/www.youtube.com\/watch?v=YhrMSyowpa8","alternative_url":"https:\/\/invidious.xyz\/watch?v=YhrMSyowpa8","date":"2021-03-22T17:43:46+00:00","traffic":98403},{"url":"https:\/\/www.youtube.com\/watch?v=eU68HjblD3w","alternative_url":"https:\/\/invidious.tube\/watch?v=eU68HjblD3w","date":"2021-03-23T07:06:42+00:00","traffic":95354},{"url":"https:\/\/www.youtube.com\/watch?v=YXZOGflwIzE","alternative_url":"https:\/\/ytprivate.com\/watch?v=YXZOGflwIzE","date":"2021-03-22T17:42:39+00:00","traffic":93068},{"url":"https:\/\/www.youtube.com\/watch?v=eOiNC0UBtLE","alternative_url":"https:\/\/invidious.xyz\/watch?v=eOiNC0UBtLE","date":"2021-03-23T07:43:46+00:00","traffic":92511},{"url":"https:\/\/www.youtube.com\/watch?v=-dDB6SNTNyk","alternative_url":"https:\/\/vid.puffyan.us\/watch?v=-dDB6SNTNyk","date":"2021-03-23T12:06:42+00:00","traffic":90832},{"url":"https:\/\/www.youtube.com\/watch?v=qlMj_Bwo2Rs","alternative_url":"https:\/\/vid.puffyan.us\/watch?v=qlMj_Bwo2Rs","date":"2021-03-22T15:42:39+00:00","traffic":84958},{"url":"https:\/\/www.youtube.com\/watch?v=_fFaZJZT5NQ","alternative_url":"https:\/\/tube.incog.host\/watch?v=_fFaZJZT5NQ","date":"2021-03-23T09:06:42+00:00","traffic":82073},{"url":"https:\/\/www.youtube.com\/watch?v=HWoRSc16AYo","alternative_url":"https:\/\/ytprivate.com\/watch?v=HWoRSc16AYo","date":"2021-03-22T14:43:46+00:00","traffic":78734},{"url":"https:\/\/www.youtube.com\/watch?v=OOrh3LmX2T4","alternative_url":"https:\/\/vid.mint.lgbt\/watch?v=OOrh3LmX2T4","date":"2021-03-22T21:57:42+00:00","traffic":78535},{"url":"https:\/\/www.youtube.com\/watch?v=rxHnjIi7qN8","alternative_url":"https:\/\/yewtu.be\/watch?v=rxHnjIi7qN8","date":"2021-03-22T21:42:39+00:00","traffic":76690},{"url":"https:\/\/www.youtube.com\/watch?v=vN2ZmQfAD3Q","alternative_url":"https:\/\/invidious.snopyta.org\/watch?v=vN2ZmQfAD3Q","date":"2021-03-22T15:43:46+00:00","traffic":74617},{"url":"https:\/\/www.youtube.com\/watch?v=7h5ReG_m1Io","alternative_url":"https:\/\/yewtu.be\/watch?v=7h5ReG_m1Io","date":"2021-03-22T16:42:39+00:00","traffic":74178},{"url":"https:\/\/www.youtube.com\/watch?v=ugcWk6cAmlI","alternative_url":"https:\/\/invidious.snopyta.org\/watch?v=ugcWk6cAmlI","date":"2021-03-23T08:43:46+00:00","traffic":72174},{"url":"https:\/\/www.youtube.com\/watch?v=_Ik3JLwF0kw","alternative_url":"https:\/\/invidious.xyz\/watch?v=_Ik3JLwF0kw","date":"2021-03-23T12:31:42+00:00","traffic":65375},{"url":"https:\/\/www.youtube.com\/watch?v=tT_F0rsf_8k","alternative_url":"https:\/\/au.ytprivate.com\/watch?v=tT_F0rsf_8k","date":"2021-03-23T04:57:42+00:00","traffic":64305},{"url":"https:\/\/www.youtube.com\/watch?v=g3qSUSzJtzc","alternative_url":"https:\/\/invidious.snopyta.org\/watch?v=g3qSUSzJtzc","date":"2021-03-22T22:57:42+00:00","traffic":61434}]